[
  {
    "_index": "test",
    "_type": "location",
    "_id": "21285",
    "_score": 8.627064,
    "_source": {
      "id": 21285,
      "uid": "1231231",
      "barangay": "Quiapo"
    }
  },
  {
    "_index": "test",
    "_type": "location",
    "_id": "32296",
    "_score": 7.191506,
    "_source": {
      "id": 32296,
      "uid": "1231313",
      "barangay": "Quiajo"
    }
  },
  {
    "_index": "test",
    "_type": "location",
    "_id": "40029",
    "_score": 5.7606287,
    "_source": {
      "id": 40029,
      "uid": "asd",
      "barangay": "Quipot"
    }
  },
  {
    "_index": "test",
    "_type": "location",
    "_id": "20981",
    "_score": 5.7559,
    "_source": {
      "id": 20981,
      "uid": "asd",
      "barangay": "Quipot"
    }
  },
  {
    "_index": "test",
    "_type": "location",
    "_id": "15626",
    "_score": 5.753205,
    "_source": {
      "id": 15626,
      "uid": "asd",
      "barangay": "Quirapi"
    }
  },
  {
    "_index": "test",
    "_type": "location",
    "_id": "34824",
    "_score": 5.7513757,
    "_source": {
      "id": 34824,
      "uid": "asd",
      "barangay": "Quipot"

    }
  },
  {
    "_index": "test",
    "_type": "location",
    "_id": "40389",
    "_score": 5.7513757,
    "_source": {
      "id": 40389,
      "uid": "asd",
      "barangay": "Quilao"
    }
  },
  {
    "_index": "test",
    "_type": "location",
    "_id": "19717",
    "_score": 5.750419,
    "_source": {
      "id": 19717,
      "uid": "asd",
      "barangay": "Quitago"
    }
  },
  {
    "_index": "test",
    "_type": "location",
    "_id": "31417",
    "_score": 5.750419,
    "_source": {
      "id": 31417,
      "uid": "asd",
      "barangay": "Quisao"
    }
  },
  {
    "_index": "test",
    "_type": "location",
    "_id": "20319",
    "_score": 5.175378,
    "_source": {
      "id": 20319,
      "uid": "asd",
      "barangay": "Quilo"
    }
  }
]

